bcsv/__init__.py
bcsv-0.0.2.dist-info/DESCRIPTION.rst
bcsv-0.0.2.dist-info/METADATA
bcsv-0.0.2.dist-info/RECORD
bcsv-0.0.2.dist-info/WHEEL
bcsv-0.0.2.dist-info/metadata.json
bcsv-0.0.2.dist-info/top_level.txt
