Metadata-Version: 2.0
Name: bcsv
Version: 0.0.2
Summary: CSV parsing and writing
Home-page: https://github.com/BlackEarth/bcsv
Author: Sean Harrison
Author-email: sah@bookgenesis.com
License: LGPL 3.0
Platform: UNKNOWN
Classifier: Development Status :: 3 - Alpha
Classifier: Intended Audience :: Developers
Classifier: License :: OSI Approved :: GNU Library or Lesser General Public License (LGPL)
Classifier: Programming Language :: Python :: 3
Provides-Extra: dev
Provides-Extra: test
